{
  "project_info": {
    "project_number": "1074000861676",
    "project_id": "miraquee-35e50",
    "storage_bucket": "miraquee-35e50.appspot.com"
  },
  "client": [
    {
      "client_info": {
        "mobilesdk_app_id": "1:1074000861676:android:0c08bb8f99fd2a92bc88c9",
        "android_client_info": {
          "package_name": "com.arpit.miraquee"
        }
      },
      "oauth_client": [
        {
          "client_id": "1074000861676-0a16fr1o3u9h5pk7004ko86e4rdor858.apps.googleusercontent.com",
          "client_type": 3
        }
      ],
      "api_key": [
        {
          "current_key": "AIzaSyAnaD-zh9oGovddSskBgYtRyHxlWad63Ls"
        }
      ],
      "services": {
        "appinvite_service": {
          "other_platform_oauth_client": [
            {
              "client_id": "1074000861676-0a16fr1o3u9h5pk7004ko86e4rdor858.apps.googleusercontent.com",
              "client_type": 3
            }
          ]
        }
      }
    }
  ],
  "configuration_version": "1"
}